scrapenhl2/__init__.py
scrapenhl2/manipulate/__init__.py
scrapenhl2/manipulate/add_onice_players.py
scrapenhl2/manipulate/combos.py
scrapenhl2/manipulate/manipulate.py
scrapenhl2/manipulate/player_log.py
scrapenhl2/plot/__init__.py
scrapenhl2/plot/defense_pairs.py
scrapenhl2/plot/forward_trios.py
scrapenhl2/plot/game_h2h.py
scrapenhl2/plot/game_timeline.py
scrapenhl2/plot/label_lines.py
scrapenhl2/plot/rolling_boxcars.py
scrapenhl2/plot/rolling_cf_gf.py
scrapenhl2/plot/team_lineup_cf.py
scrapenhl2/plot/team_score_shot_rate.py
scrapenhl2/plot/team_score_state_toi.py
scrapenhl2/plot/usage.py
scrapenhl2/plot/visualization_helper.py
scrapenhl2/plot/visualize_app.py
scrapenhl2/plot/app/__init__.py
scrapenhl2/plot/app/game_page.py
scrapenhl2/plot/app/game_views.py
scrapenhl2/plot/app/help_views.py
scrapenhl2/plot/app/init_old.py
scrapenhl2/plot/app/player_page.py
scrapenhl2/plot/app/player_views.py
scrapenhl2/plot/app/run.py
scrapenhl2/plot/app/stat_views.py
scrapenhl2/plot/app/team_page.py
scrapenhl2/plot/app/team_views.py
scrapenhl2/scrape/__init__.py
scrapenhl2/scrape/autoupdate.py
scrapenhl2/scrape/check_game_data.py
scrapenhl2/scrape/events.py
scrapenhl2/scrape/games.py
scrapenhl2/scrape/general_helpers.py
scrapenhl2/scrape/manipulate_schedules.py
scrapenhl2/scrape/organization.py
scrapenhl2/scrape/parse_pbp.py
scrapenhl2/scrape/parse_toi.py
scrapenhl2/scrape/players.py
scrapenhl2/scrape/schedules.py
scrapenhl2/scrape/scrape_pbp.py
scrapenhl2/scrape/scrape_toi.py
scrapenhl2/scrape/team_info.py
scrapenhl2/scrape/teams.py
scrapenhl2-0.4.1.dist-info/DESCRIPTION.rst
scrapenhl2-0.4.1.dist-info/METADATA
scrapenhl2-0.4.1.dist-info/RECORD
scrapenhl2-0.4.1.dist-info/WHEEL
scrapenhl2-0.4.1.dist-info/metadata.json
scrapenhl2-0.4.1.dist-info/top_level.txt
tests/__init__.py
tests/conftest.py
tests/exception_decor_tests.py
tests/manipulate_tests.py
tests/scrape_game_tests.py
tests/scrape_setup_tests.py
tests/test_schedule.py
tests/visualize_game_tests.py
tests/visualize_tests.py
