Metadata-Version: 2.0
Name: scrapenhl2
Version: 0.4.1
Summary: scrapenhl2 is a python package for scraping and manipulating NHL data pulled from the NHL website.
Home-page: https://github.com/muneebalam/scrapenhl2
Author: Muneeb Alam
Author-email: muneeb.alam@gmail.com
License: MIT
Keywords: nhl
Platform: UNKNOWN
Classifier: Development Status :: 2 - Pre-Alpha
Classifier: Intended Audience :: Science/Research
Classifier: License :: OSI Approved :: MIT License
Classifier: Programming Language :: Python :: 3
Requires-Dist: arrow
Requires-Dist: beautifulsoup4 (==4.5.3)
Requires-Dist: dash
Requires-Dist: dash-core-components
Requires-Dist: dash-html-components
Requires-Dist: dash-renderer
Requires-Dist: feather-format
Requires-Dist: flask
Requires-Dist: fuzzywuzzy
Requires-Dist: halo
Requires-Dist: html-table-extractor
Requires-Dist: matplotlib
Requires-Dist: numpy
Requires-Dist: pandas
Requires-Dist: plotly
Requires-Dist: pyarrow
Requires-Dist: pytest
Requires-Dist: pytest-cov
Requires-Dist: pytest-mock
Requires-Dist: python-Levenshtein
Requires-Dist: requests
Requires-Dist: scikit-learn
Requires-Dist: scipy
Requires-Dist: seaborn
Requires-Dist: sphinx
Requires-Dist: tqdm
